setup.cfg
setup.py
mmmbop/MBTile.py
mmmbop/MBTilesMetadata.py
mmmbop/__init__.py
mmmbop/cli.py
mmmbop/config.py
mmmbop/util.py
mmmbop.egg-info/PKG-INFO
mmmbop.egg-info/SOURCES.txt
mmmbop.egg-info/dependency_links.txt
mmmbop.egg-info/entry_points.txt
mmmbop.egg-info/requires.txt
mmmbop.egg-info/top_level.txt
mmmbop/templates/map.html