Metadata-Version: 1.1
Name: mmmbop
Version: 0.1.8
Summary: View MBtiles on localhost
Home-page: https://github.com/l-r/mmmbop
Author: Laurier Rochon
Author-email: l@pwd.io
License: UNKNOWN
Download-URL: https://github.com/l-r/mmmbop/tarball/0.1.8
Keywords: MBtiles
Platform: UNKNOWN
